kroissan
