Metadata-Version: 1.0
Name: kroissan
Version: 0.2.1
Summary: YAML spreadsheet
Home-page: https://gitlab.com/kroissan/kroissan
Author: Noel Martignoni
Author-email: noel@martignoni.fr
License: UNKNOWN
Platform: UNKNOWN
